Metadata-Version: 2.1
Name: steamsales
Version: 0.2
Summary: Wrapper for PrepareYourWallet
Home-page: https://github.com/zedyn/steamsales
Author: zédyN
Author-email: zedyn@protonmail.com
License: UNKNOWN
Project-URL: Bug Tracker, https://github.com/zedyn/steamsales/issues
Platform: UNKNOWN
Classifier: Programming Language :: Python :: 3
Classifier: License :: OSI Approved :: MIT License
Classifier: Operating System :: OS Independent
Requires-Python: >=3.6
